pegen/__init__.py
pegen/__main__.py
pegen/build.py
pegen/first_sets.py
pegen/grammar.py
pegen/grammar_parser.py
pegen/grammar_visualizer.py
pegen/metagrammar.gram
pegen/parser.py
pegen/parser_generator.py
pegen/py.typed
pegen/python_generator.py
pegen/sccutils.py
pegen/tokenizer.py
pegen/utils.py
pegen/validator.py
pegen/web.py
pegen/templates/index.html
pegen-0.3.0.dist-info/LICENSE
pegen-0.3.0.dist-info/METADATA
pegen-0.3.0.dist-info/WHEEL
pegen-0.3.0.dist-info/top_level.txt
pegen-0.3.0.dist-info/RECORD
