Metadata-Version: 2.1
Name: pegen
Version: 0.3.0
Summary: CPython's PEG parser generator
Author: Guido van Rossum
Author-email: Pablo Galindo <pablogsal@gmail.com>, Lysandros Nikolaou <lisandrosnik@gmail.com>
Maintainer-email: "Matthieu C. Dartiailh" <m.dartiailh@gmail.com>
License: MIT License
Project-URL: homepage, https://github.com/we-like-parsers/pegen
Project-URL: documentation, https://we-like-parsers.github.io/pegen/
Project-URL: source, https://github.com/we-like-parsers/pegen
Project-URL: changelog, https://github.com/we-like-parsers/pegen/releasenotes.rst
Project-URL: bug_reports, https://github.com/we-like-parsers/pegen/issues
Keywords: parser,CPython,PEG,pegen
Classifier: Development Status :: 3 - Alpha
Classifier: Intended Audience :: Developers
Classifier: Topic :: Software Development :: Compilers
Classifier: License :: OSI Approved :: MIT License
Classifier: Programming Language :: Python :: 3.8
Classifier: Programming Language :: Python :: 3.9
Classifier: Programming Language :: Python :: 3.10
Classifier: Programming Language :: Python :: 3 :: Only
Requires-Python: <4,>=3.8
License-File: LICENSE
Provides-Extra: docs
Requires-Dist: sphinx; extra == "docs"
Requires-Dist: sphinx-copybutton; extra == "docs"
Requires-Dist: furo; extra == "docs"
Provides-Extra: lint
Requires-Dist: black; extra == "lint"
Requires-Dist: flake8; extra == "lint"
Requires-Dist: mypy; extra == "lint"
Provides-Extra: test
Requires-Dist: pytest; extra == "test"
Requires-Dist: pytest-cov; extra == "test"
Provides-Extra: memory
Requires-Dist: psutil; extra == "memory"
Provides-Extra: web
Requires-Dist: flask; extra == "web"
Requires-Dist: flask-wtf; extra == "web"
